setup.py
pod_tree/__init__.py
pod_tree/main.py
pod_tree.egg-info/PKG-INFO
pod_tree.egg-info/SOURCES.txt
pod_tree.egg-info/dependency_links.txt
pod_tree.egg-info/entry_points.txt
pod_tree.egg-info/top_level.txt